nestedmapping/__init__.py
nestedmapping/class_wrapper.py
nestedmapping/ipython.py
nestedmapping/nested_mapping.py
nestedmapping/nested_mapping_access.py
nestedmapping/typing.py
nestedmapping/visitor.py
nestedmapping/tools/__init__.py
nestedmapping/tools/filter.py
nestedmapping/tools/map.py
nestedmapping/tools/match.py
nestedmapping/tools/reorder_key.py
nestedmapping-0.9.9.dist-info/licenses/LICENSE
nestedmapping-0.9.9.dist-info/METADATA
nestedmapping-0.9.9.dist-info/WHEEL
nestedmapping-0.9.9.dist-info/top_level.txt
nestedmapping-0.9.9.dist-info/RECORD
