Metadata-Version: 2.4
Name: nestedmapping
Version: 0.9.9
Summary: The package to work with nested dictionaries supporing list/set as keys
Author-email: DAGFlow Team <dagflow@jinr.ru>
Maintainer-email: DAGFlow Team <dagflow@jinr.ru>
License-Expression: MIT
Project-URL: homepage, https://github.com/dagflow-team/nestedmapping
Project-URL: repository, https://github.com/dagflow-team/nestedmapping
Project-URL: documentation, https://github.com/dagflow-team/nestedmapping/wiki
Project-URL: Bug Tracker, https://github.com/dagflow-team/nestedmapping/issues
Requires-Python: >=3.11
License-File: LICENSE
Requires-Dist: numpy
Requires-Dist: ordered-set
Provides-Extra: dev
Requires-Dist: pytest; extra == "dev"
Requires-Dist: pytest-cov; extra == "dev"
Requires-Dist: coverage; extra == "dev"
Dynamic: license-file
